Metadata-Version: 1.0
Name: seppepi-distributions
Version: 0.1
Summary: Gaussian distributions
Home-page: UNKNOWN
Author: Seppe Pi
Author-email: seppe.pintens@gmail.com
License: UNKNOWN
Platform: UNKNOWN
